clicktypes/__init__.py
clicktypes/decorator.py
click_validators-0.2.1.dist-info/LICENSE
click_validators-0.2.1.dist-info/METADATA
click_validators-0.2.1.dist-info/WHEEL
click_validators-0.2.1.dist-info/RECORD
