Metadata-Version: 2.1
Name: click-validators
Version: 0.2.1
Summary: additional types for `click` parameter using `validators`.
License: MIT
Keywords: click,validators
Author: Christoph Dörrer
Author-email: d-chris@web.de
Requires-Python: >=3.9,<4.0
Classifier: License :: OSI Approved :: MIT License
Classifier: Operating System :: OS Independent
Classifier: Programming Language :: Python :: 3
Classifier: Programming Language :: Python :: 3.9
Classifier: Programming Language :: Python :: 3.10
Classifier: Programming Language :: Python :: 3.11
Classifier: Programming Language :: Python :: 3.12
Classifier: Programming Language :: Python :: 3.13
Provides-Extra: crypto-eth-addresses
Provides-Extra: eth
Requires-Dist: click (>=8.1.8)
Requires-Dist: eth-hash[pycryptodome] (>=0.7.0) ; extra == "crypto-eth-addresses" or extra == "eth"
Requires-Dist: validators (>=0.34.0)
Project-URL: documentation, https://d-chris.github.io/click-validators
Project-URL: repository, https://github.com/d-chris/click-validators
